pydoctordroid/__init__.py
pydoctordroid/_event_exporter.py
pydoctordroid/_events.py
pydoctordroid/_logger.py
pydoctordroid/_value.py
pydoctordroid/lib.py
pydoctordroid-0.1.1.dist-info/LICENSE.txt
pydoctordroid-0.1.1.dist-info/METADATA
pydoctordroid-0.1.1.dist-info/WHEEL
pydoctordroid-0.1.1.dist-info/top_level.txt
pydoctordroid-0.1.1.dist-info/RECORD
