Metadata-Version: 2.1
Name: pydoctordroid
Version: 0.1.1
Summary: Code Marker Library from Doctor Droid to generate custom events
Author: Dipesh Mittal
Author-email: dipesh@drdroid.io
License: MIT
Classifier: Programming Language :: Python :: 3
Classifier: License :: OSI Approved :: MIT License
Classifier: Operating System :: OS Independent
Requires-Python: >=3.6
License-File: LICENSE.txt
Requires-Dist: urllib3 (>=1.26.11)
